{"cameraMode":{"drawMode":0,"name":"Shaded","section":"Shading Mode"},"sceneLighting":false,"audioPlay":false,"sceneViewState":{"m_AlwaysRefresh":false,"showFog":true,"showSkybox":false,"showFlares":true,"showImageEffects":true,"showParticleSystems":true,"showVisualEffectGraphs":true,"m_FxEnabled":true},"in2DMode":false,"pivot":{"x":2.8610782623291017,"y":0.5373543500900269,"z":-3.2805914878845217},"rotation":{"x":0.15974797308444978,"y":-0.14894059300422669,"z":0.02438579685986042,"w":0.9755549430847168},"size":0.6500935554504395,"orthographic":false}